{
    "VMEModuleType": 19,
    "VMEModuleName": "MDPP-16_PADC",
    "HeaderDTypeMask": 4026531840,
    "HeaderDType": 4,
    "HeaderDTypeShift": 28,
    "LowTimestampDTypeMask": 3221225472,
    "LowTimestampDType": 3,
    "LowTimestampDTypeShift": 30,
    "HighTimestampDTypeMask": 4026531840,
    "HighTimestampDType": 2,
    "HighTimestampDTypeShift": 28,
    "DataDTypeMask": 4026531840,
    "DataDType": 1,
    "DataDTypeShift": 28,
    "OptDTypeMask": 4026531840,
    "OptDType": 1,
    "OptDTypeShift": 28,
    "ID_Mask": 16711680,
    "ID_Shift": 16,
    "ADC_RES_Mask": 7168,
    "ADC_RES_Shift": 10,
    "TDC_RES_Mask": 57344,
    "TDC_RES_Shift": 13,
    "LowTimestamp_Mask": 1073741823,
    "LowTimestamp_Shift": 0,
    "HighTimestamp_Mask": 65535,
    "HighTimestamp_Shift": 30,
    "Channel_Mask": 4128768,
    "Channel_Shift": 16,
    "Data_Mask": 65535,
    "Data_Shift": 0,
    "Overflow_Mask": 4194304,
    "Overflow_Shift": 0,
    "Pileup_Mask": 0,
    "Pileup_Shift": 0,
    "OutOfRange_Mask": 0,
    "OutOfRange_Shift": 0,
    "Reset_Mask": 0,
    "Reset_Shift": 0,
    "Opt1_Mask": 0,
    "Opt1_Shift": 0,
    "Opt2_Mask": 0,
    "Opt2_Shift": 0
}
